LICENSE
MANIFEST.in
README.rst
requirements.txt
setup.cfg
setup.py
examples/__init__.py
examples/connections_simulation.py
examples/peer_request_response.py
examples/receive_test.py
examples/send_test.py
gossip/__init__.py
gossip/gossip_main.py
gossip/communication/__init__.py
gossip/communication/client_receiver.py
gossip/communication/client_sender.py
gossip/communication/connection.py
gossip/communication/server.py
gossip/control/__init__.py
gossip/control/api_controller.py
gossip/control/api_registrations.py
gossip/control/convert.py
gossip/control/message_cache.py
gossip/control/p2p_controller.py
gossip/util/__init__.py
gossip/util/byte_formatting.py
gossip/util/config_parser.py
gossip/util/exceptions.py
gossip/util/message.py
gossip/util/message_code.py
gossip/util/packing.py
gossip/util/queue_item_types.py
gossip_python.egg-info/PKG-INFO
gossip_python.egg-info/SOURCES.txt
gossip_python.egg-info/dependency_links.txt
gossip_python.egg-info/top_level.txt
tests/communication/__init__.py
tests/communication/test_connection_pool.py
tests/util/__init__.py
tests/util/test_byte_formatting.py
tests/util/test_message.py