Metadata-Version: 1.1
Name: gossip-python
Version: 0.0.1
Summary: Python module for gossip integration
Home-page: https://stash.bwk-technik.de/projects/PTP/repos/p2p-code/
Author: Anselm Binninger | Ralph Oliver Schaumann | Thomas Maier
Author-email: anselm.binninger@tum.de | tom.maier@tum.de
License: Copyright 2016 Anselm Binninger, Thomas Maier, Ralph Schaumann
